LICENSE
MANIFEST.in
README.txt
setup.py
bpn/__init__.py
bpn/launcher.py
bpn/gui/__init__.py
bpn/gui/frame.py
bpn/test/__init__.py
btc_price_notifier.egg-info/PKG-INFO
btc_price_notifier.egg-info/SOURCES.txt
btc_price_notifier.egg-info/dependency_links.txt
btc_price_notifier.egg-info/entry_points.txt
btc_price_notifier.egg-info/requires.txt
btc_price_notifier.egg-info/top_level.txt