Metadata-Version: 1.1
Name: btc-price-notifier
Version: 0.0.1a5
Summary: Bitcoin price notifier
Home-page: https://github.com/muchu1983/btc-price-notifier
Author: MuChu Hsu
Author-email: muchu1983@gmail.com
License: MIT License
Download-URL: https://pypi.python.org/pypi/btc-price-notifier
Platform: python 3.6
Classifier: Development Status :: 3 - Alpha
Classifier: Environment :: Win32 (MS Windows)
Classifier: Environment :: X11 Applications :: GTK
Classifier: Intended Audience :: End Users/Desktop
Classifier: Intended Audience :: Developers
Classifier: License :: OSI Approved :: MIT License
Classifier: Natural Language :: Chinese (Traditional)
Classifier: Natural Language :: Chinese (Simplified)
Classifier: Natural Language :: English
Classifier: Operating System :: Microsoft :: Windows
Classifier: Operating System :: POSIX :: Linux
Classifier: Programming Language :: Python :: 3.6
Classifier: Topic :: Internet :: WWW/HTTP
